facturx/__init__.py
facturx/facturx.py
facturx/scripts/__init__.py
facturx/scripts/pdfextractxml.py
facturx/scripts/pdfgen.py
facturx/scripts/webservice.py
facturx/scripts/xmlcheck.py
facturx/xmp/Factur-X_extension_schema.xmp
facturx/xmp/ZUGFeRD_extension_schema.xmp
facturx/xsd/facturx-basic/Factur-X_1.08_BASIC.xsd
facturx/xsd/facturx-basic/Factur-X_1.08_BASIC_urn_un_unece_uncefact_data_standard_QualifiedDataType_100.xsd
facturx/xsd/facturx-basic/Factur-X_1.08_BASIC_urn_un_unece_uncefact_data_standard_ReusableAggregateBusinessInformationEntity_100.xsd
facturx/xsd/facturx-basic/Factur-X_1.08_BASIC_urn_un_unece_uncefact_data_standard_UnqualifiedDataType_100.xsd
facturx/xsd/facturx-basicwl/Factur-X_1.08_BASICWL.xsd
facturx/xsd/facturx-basicwl/Factur-X_1.08_BASICWL_urn_un_unece_uncefact_data_standard_QualifiedDataType_100.xsd
facturx/xsd/facturx-basicwl/Factur-X_1.08_BASICWL_urn_un_unece_uncefact_data_standard_ReusableAggregateBusinessInformationEntity_100.xsd
facturx/xsd/facturx-basicwl/Factur-X_1.08_BASICWL_urn_un_unece_uncefact_data_standard_UnqualifiedDataType_100.xsd
facturx/xsd/facturx-en16931/Factur-X_1.08_EN16931.xsd
facturx/xsd/facturx-en16931/Factur-X_1.08_EN16931_urn_un_unece_uncefact_data_standard_QualifiedDataType_100.xsd
facturx/xsd/facturx-en16931/Factur-X_1.08_EN16931_urn_un_unece_uncefact_data_standard_ReusableAggregateBusinessInformationEntity_100.xsd
facturx/xsd/facturx-en16931/Factur-X_1.08_EN16931_urn_un_unece_uncefact_data_standard_UnqualifiedDataType_100.xsd
facturx/xsd/facturx-extended/Factur-X_1.08_EXTENDED.xsd
facturx/xsd/facturx-extended/Factur-X_1.08_EXTENDED_urn_un_unece_uncefact_data_standard_QualifiedDataType_100.xsd
facturx/xsd/facturx-extended/Factur-X_1.08_EXTENDED_urn_un_unece_uncefact_data_standard_ReusableAggregateBusinessInformationEntity_100.xsd
facturx/xsd/facturx-extended/Factur-X_1.08_EXTENDED_urn_un_unece_uncefact_data_standard_UnqualifiedDataType_100.xsd
facturx/xsd/facturx-minimum/Factur-X_1.08_MINIMUM.xsd
factur_x-3.15.dist-info/METADATA
factur_x-3.15.dist-info/WHEEL
factur_x-3.15.dist-info/entry_points.txt
factur_x-3.15.dist-info/licenses/LICENSE
factur_x-3.15.dist-info/RECORD
