Metadata-Version: 2.3
Name: factur-x
Version: 3.15
Summary: Factur-X and Order-X: electronic invoicing and ordering standards
Project-URL: Homepage, https://github.com/akretion/factur-x
Project-URL: Source, https://github.com/akretion/factur-x
Project-URL: Issues, https://github.com/akretion/factur-x/issues
Author-email: Alexis de Lattre <alexis.delattre@akretion.com>
License: Copyright (c) 2016-2023, Alexis de Lattre <alexis.delattre@akretion.com>
Keywords: Factur-X,Order-X,ZUGFeRD,e-invoice,e-procurement
Classifier: Development Status :: 5 - Production/Stable
Classifier: Intended Audience :: Developers
Classifier: License :: OSI Approved :: BSD License
Classifier: Operating System :: OS Independent
Classifier: Programming Language :: Python
Classifier: Topic :: Office/Business :: Financial :: Accounting
Requires-Python: >=3.7
Requires-Dist: importlib-resources; python_version < '3.9'
Requires-Dist: lxml
Requires-Dist: pypdf>=5.3.0
